cffs/__init__.py
cffs/combi_expressions.py
cffs/combi_solving.py
cffs/expressions.py
cffs/feature_qualities.py
cffs/solving.py
cffs-1.0.0.dist-info/LICENSE
cffs-1.0.0.dist-info/METADATA
cffs-1.0.0.dist-info/WHEEL
cffs-1.0.0.dist-info/top_level.txt
cffs-1.0.0.dist-info/RECORD
