Metadata-Version: 2.1
Name: cffs
Version: 1.0.0
Summary: Constrained feature selection
Author-email: Jakob Bach <jakob.bach.ka@gmail.com>
Project-URL: Homepage, https://github.com/Jakob-Bach/Constrained-Filter-Feature-Selection/tree/master/src/cffs_package
Project-URL: Issues, https://github.com/Jakob-Bach/Constrained-Filter-Feature-Selection/issues
Keywords: feature selection,constraints
Classifier: Programming Language :: Python :: 3
Classifier: License :: OSI Approved :: MIT License
Classifier: Operating System :: OS Independent
Requires-Python: >=3.7
License-File: LICENSE
Requires-Dist: pandas >=1.1.3
Requires-Dist: scikit-learn >=0.23.2
Requires-Dist: z3-solver >=4.8.9.0
